rus_roulette/__init__.py
rus_roulette/roulette.py
rus_roulette-1.1.2.dist-info/METADATA
rus_roulette-1.1.2.dist-info/WHEEL
rus_roulette-1.1.2.dist-info/RECORD
